pulp_certguard/__init__.py
pulp_certguard/pytest_plugin.py
pulp_certguard/app/__init__.py
pulp_certguard/app/models.py
pulp_certguard/app/serializers.py
pulp_certguard/app/viewsets.py
pulp_certguard/app/migrations/0001_initial.py
pulp_certguard/app/migrations/0002_alter_rhsmcertguard_contentguard_ptr_and_more.py
pulp_certguard/app/migrations/__init__.py
pulp_certguard/rhsm/__init__.py
pulp_certguard/rhsm/rhsm_check_path.py
pulp_certguard/tests/__init__.py
pulp_certguard/tests/functional/__init__.py
pulp_certguard/tests/functional/conftest.py
pulp_certguard/tests/functional/constants.py
pulp_certguard/tests/functional/api/__init__.py
pulp_certguard/tests/functional/api/test_rhsm_certguard.py
pulp_certguard/tests/functional/api/test_x509_certguard.py
pulp_certguard/tests/functional/artifacts/rhsm/katello-default-ca.crt
pulp_certguard/tests/functional/artifacts/rhsm/katello-default-ca.key
pulp_certguard/tests/functional/artifacts/rhsm/trusted_but_expired.pem
pulp_certguard/tests/functional/artifacts/rhsm/uber.cert
pulp_certguard/tests/functional/artifacts/rhsm/untrusted_cert-key.pem
pulp_certguard/tests/functional/artifacts/rhsm/untrusted_cert.pem
pulp_certguard/tests/functional/artifacts/rhsm/v1/1514454871848760713-key.pem
pulp_certguard/tests/functional/artifacts/rhsm/v1/1514454871848760713.pem
pulp_certguard/tests/functional/artifacts/rhsm/v1/159442575569388840-key.pem
pulp_certguard/tests/functional/artifacts/rhsm/v1/159442575569388840.pem
pulp_certguard/tests/functional/artifacts/rhsm/v3/4260035510644027985-key.pem
pulp_certguard/tests/functional/artifacts/rhsm/v3/4260035510644027985.pem
pulp_certguard/tests/functional/artifacts/rhsm/v3/5527980418107729172-key.pem
pulp_certguard/tests/functional/artifacts/rhsm/v3/5527980418107729172.pem
pulp_certguard/tests/functional/artifacts/thirdparty_ca/genca.sh
pulp_certguard/tests/functional/artifacts/thirdparty_ca/certificates/ca.pem
pulp_certguard/tests/functional/artifacts/thirdparty_ca/keys/ca.pem
pulpcore-3.100.0.dist-info/licenses/LICENSE
pulpcore-3.100.0.dist-info/METADATA
pulpcore-3.100.0.dist-info/WHEEL
pulpcore-3.100.0.dist-info/entry_points.txt
pulpcore-3.100.0.dist-info/top_level.txt
pulpcore-3.100.0.dist-info/RECORD
